multipeer.py
pythonista_multipeer-1.0.1.dist-info/LICENSE
pythonista_multipeer-1.0.1.dist-info/WHEEL
pythonista_multipeer-1.0.1.dist-info/METADATA
pythonista_multipeer-1.0.1.dist-info/RECORD
