Metadata-Version: 2.1
Name: pythonista-multipeer
Version: 1.0.1
Summary: Multipeer connectivity for the Pythonista iOS app
Home-page: https://github.com/mikaelho/multipeer
License: TheUnlicense
Author: Mikael Honkala
Author-email: mikael.honkala@gmail.com
Classifier: Operating System :: iOS
